setup.py
assignmentsptyma/__init__.py
assignmentsptyma/azbook_scrape.py
assignmentsptyma/main.py
assignmentsptyma/sastobook_scrape.py
assignmentsptyma.egg-info/PKG-INFO
assignmentsptyma.egg-info/SOURCES.txt
assignmentsptyma.egg-info/dependency_links.txt
assignmentsptyma.egg-info/not-zip-safe
assignmentsptyma.egg-info/requires.txt
assignmentsptyma.egg-info/top_level.txt