Metadata-Version: 1.0
Name: assignmentsptyma
Version: 0.9
Summary: The funniest joke in the world
Home-page: UNKNOWN
Author: UNKNOWN
Author-email: UNKNOWN
License: UNKNOWN
Platform: UNKNOWN
